xyz_aliyun/__init__.py
xyz_aliyun/dns.py
xyz_aliyun/ecs.py
xyz_aliyun/ess.py
xyz_aliyun/oss.py
xyz_aliyun/sts.py
xyz_aliyun/utils.py
xyz_aliyun-0.0.8.dist-info/METADATA
xyz_aliyun-0.0.8.dist-info/WHEEL
xyz_aliyun-0.0.8.dist-info/top_level.txt
xyz_aliyun-0.0.8.dist-info/RECORD
