Metadata-Version: 2.1
Name: xyz-aliyun
Version: 0.0.8
Summary: aliyun utils
Home-page: https://github.com/szuprefix/py-xyz-aliyun
Author: XYZSaas
Author-email: szuprefix@126.com
License: MIT
Classifier: Environment :: Web Environment
Classifier: Intended Audience :: Developers
Classifier: Operating System :: OS Independent
Classifier: Topic :: Text Processing :: Indexing
Classifier: Topic :: Utilities
Classifier: Topic :: Internet
Classifier: Topic :: Software Development :: Libraries :: Python Modules
Classifier: Programming Language :: Python
Classifier: Programming Language :: Python :: 2
Classifier: Programming Language :: Python :: 2.7
Classifier: Programming Language :: Python :: 3
Classifier: Programming Language :: Python :: 3.5
Classifier: Programming Language :: Python :: 3.6
Classifier: Programming Language :: Python :: 3.7
Classifier: Programming Language :: Python :: 3.8
Requires-Dist: django (>=1.11.2)
Requires-Dist: oss2
Requires-Dist: aliyun-python-sdk-sts
Requires-Dist: aliyun-python-sdk-ecs
Requires-Dist: alibabacloud-alidns20150109
